radio_manager/__init__.py
radio_manager/__version__.py
radio_manager/cli.py
radio_manager/audio_proxy/__init__.py
radio_manager/audio_proxy/proxy.py
radio_manager/base/__init__.py
radio_manager/base/radio.py
radio_manager/uniden/__init__.py
radio_manager/uniden/bcd996p2.py
radio_manager/uniden/rtsp.py
radio_manager/uniden/sds200.py
radio_manager/utils/__init__.py
radio_manager/utils/retry.py
radio_manager-0.2.3.dist-info/licenses/LICENSE
radio_manager-0.2.3.dist-info/METADATA
radio_manager-0.2.3.dist-info/WHEEL
radio_manager-0.2.3.dist-info/entry_points.txt
radio_manager-0.2.3.dist-info/top_level.txt
radio_manager-0.2.3.dist-info/RECORD
