Metadata-Version: 2.4
Name: radio-manager
Version: 0.2.3
Summary: A unified library for controlling various radio devices (receivers and transceivers)
Author-email: "Thomas D. Stearn" <tomn2tsr@gmail.com>
License: MIT
Project-URL: Homepage, https://github.com/tomn2tsr/radio-manager
Project-URL: Issues, https://github.com/tomn2tsr/radio-manager/issues
Classifier: Development Status :: 3 - Alpha
Classifier: Intended Audience :: Developers
Classifier: License :: OSI Approved :: MIT License
Classifier: Programming Language :: Python :: 3
Classifier: Programming Language :: Python :: 3.8
Classifier: Programming Language :: Python :: 3.9
Classifier: Programming Language :: Python :: 3.10
Classifier: Programming Language :: Python :: 3.11
Classifier: Programming Language :: Python :: 3.12
Requires-Python: >=3.8
License-File: LICENSE
Requires-Dist: pyserial>=3.4
Requires-Dist: pyyaml>=6.0
Provides-Extra: audio
Requires-Dist: pyaudio>=0.2.11; extra == "audio"
Provides-Extra: dev
Requires-Dist: pytest>=7.0; extra == "dev"
Requires-Dist: pytest-cov>=4.0; extra == "dev"
Requires-Dist: black>=23.0; extra == "dev"
Requires-Dist: flake8>=6.0; extra == "dev"
Requires-Dist: mypy>=1.0; extra == "dev"
Dynamic: license-file
